maxbotapi/__init__.py
maxbotapi/api.py
maxbotapi-1.1.4.dist-info/licenses/LICENSE
maxbotapi-1.1.4.dist-info/METADATA
maxbotapi-1.1.4.dist-info/WHEEL
maxbotapi-1.1.4.dist-info/top_level.txt
maxbotapi-1.1.4.dist-info/RECORD
